{"primaryContentSections":[{"kind":"declarations","declarations":[{"tokens":[{"kind":"keyword","text":"enum"},{"kind":"text","text":" "},{"kind":"identifier","text":"RawPlugEventType"}],"languages":["swift"],"platforms":["iOS"]}]}],"schemaVersion":{"major":0,"minor":3,"patch":0},"sections":[],"variants":[{"paths":["\/documentation\/divar\/rawplugeventtype"],"traits":[{"interfaceLanguage":"swift"}]}],"relationshipsSections":[{"identifiers":["doc:\/\/com.Divar.DivarClient\/SQ","doc:\/\/com.Divar.DivarClient\/SH","doc:\/\/com.Divar.DivarClient\/SY","doc:\/\/com.Divar.DivarClient\/s8SendableP"],"kind":"relationships","title":"Conforms To","type":"conformsTo"}],"identifier":{"url":"doc:\/\/com.Divar.DivarClient\/documentation\/Divar\/RawPlugEventType","interfaceLanguage":"swift"},"topicSections":[{"title":"Enumeration Cases","identifiers":["doc:\/\/com.Divar.DivarClient\/documentation\/Divar\/RawPlugEventType\/Approved","doc:\/\/com.Divar.DivarClient\/documentation\/Divar\/RawPlugEventType\/ChatSelectConversation","doc:\/\/com.Divar.DivarClient\/documentation\/Divar\/RawPlugEventType\/ChatSettingClicked","doc:\/\/com.Divar.DivarClient\/documentation\/Divar\/RawPlugEventType\/ChatSettingsItemClicked","doc:\/\/com.Divar.DivarClient\/documentation\/Divar\/RawPlugEventType\/Decline","doc:\/\/com.Divar.DivarClient\/documentation\/Divar\/RawPlugEventType\/DeleteConversations","doc:\/\/com.Divar.DivarClient\/documentation\/Divar\/RawPlugEventType\/DivarForBusinesses","doc:\/\/com.Divar.DivarClient\/documentation\/Divar\/RawPlugEventType\/Notification","doc:\/\/com.Divar.DivarClient\/documentation\/Divar\/RawPlugEventType\/PostchiNotification","doc:\/\/com.Divar.DivarClient\/documentation\/Divar\/RawPlugEventType\/PostponeStep","doc:\/\/com.Divar.DivarClient\/documentation\/Divar\/RawPlugEventType\/PromotePostPlan","doc:\/\/com.Divar.DivarClient\/documentation\/Divar\/RawPlugEventType\/RPActionCatchDeepLink","doc:\/\/com.Divar.DivarClient\/documentation\/Divar\/RawPlugEventType\/RPActionVoipAnswer","doc:\/\/com.Divar.DivarClient\/documentation\/Divar\/RawPlugEventType\/RPActionVoipClick","doc:\/\/com.Divar.DivarClient\/documentation\/Divar\/RawPlugEventType\/RPActionVoipIncoming","doc:\/\/com.Divar.DivarClient\/documentation\/Divar\/RawPlugEventType\/RPActionVoipInit","doc:\/\/com.Divar.DivarClient\/documentation\/Divar\/RawPlugEventType\/RPActionVoipReady","doc:\/\/com.Divar.DivarClient\/documentation\/Divar\/RawPlugEventType\/RPActionVoipTerminate","doc:\/\/com.Divar.DivarClient\/documentation\/Divar\/RawPlugEventType\/RPBack","doc:\/\/com.Divar.DivarClient\/documentation\/Divar\/RawPlugEventType\/RPBookmarkDidRemoveFromList","doc:\/\/com.Divar.DivarClient\/documentation\/Divar\/RawPlugEventType\/RPBulkLadderChoice","doc:\/\/com.Divar.DivarClient\/documentation\/Divar\/RawPlugEventType\/RPBuyerInspectionRequest","doc:\/\/com.Divar.DivarClient\/documentation\/Divar\/RawPlugEventType\/RPCHatAttachmentItemDidSelect","doc:\/\/com.Divar.DivarClient\/documentation\/Divar\/RawPlugEventType\/RPCallInChatDidSelect","doc:\/\/com.Divar.DivarClient\/documentation\/Divar\/RawPlugEventType\/RPCategoryItemDidSelect","doc:\/\/com.Divar.DivarClient\/documentation\/Divar\/RawPlugEventType\/RPChatAttachmentDidSelect","doc:\/\/com.Divar.DivarClient\/documentation\/Divar\/RawPlugEventType\/RPChatCallCheckDidSelect","doc:\/\/com.Divar.DivarClient\/documentation\/Divar\/RawPlugEventType\/RPChatDidSendImage","doc:\/\/com.Divar.DivarClient\/documentation\/Divar\/RawPlugEventType\/RPChatFormatNotSupported","doc:\/\/com.Divar.DivarClient\/documentation\/Divar\/RawPlugEventType\/RPChatIsTyping","doc:\/\/com.Divar.DivarClient\/documentation\/Divar\/RawPlugEventType\/RPChatMessageEdit","doc:\/\/com.Divar.DivarClient\/documentation\/Divar\/RawPlugEventType\/RPChatNotificationDidReceive","doc:\/\/com.Divar.DivarClient\/documentation\/Divar\/RawPlugEventType\/RPChatReportSpamDidSelect","doc:\/\/com.Divar.DivarClient\/documentation\/Divar\/RawPlugEventType\/RPChatSuggestionMessage","doc:\/\/com.Divar.DivarClient\/documentation\/Divar\/RawPlugEventType\/RPChatVoiceMessage","doc:\/\/com.Divar.DivarClient\/documentation\/Divar\/RawPlugEventType\/RPChooseMap","doc:\/\/com.Divar.DivarClient\/documentation\/Divar\/RawPlugEventType\/RPCityDidChange","doc:\/\/com.Divar.DivarClient\/documentation\/Divar\/RawPlugEventType\/RPClickAgencyInPost","doc:\/\/com.Divar.DivarClient\/documentation\/Divar\/RawPlugEventType\/RPClickBaladPromotion","doc:\/\/com.Divar.DivarClient\/documentation\/Divar\/RawPlugEventType\/RPClickBlogPost","doc:\/\/com.Divar.DivarClient\/documentation\/Divar\/RawPlugEventType\/RPClickBrandPosts","doc:\/\/com.Divar.DivarClient\/documentation\/Divar\/RawPlugEventType\/RPClickBrandType","doc:\/\/com.Divar.DivarClient\/documentation\/Divar\/RawPlugEventType\/RPClickBulkLadder","doc:\/\/com.Divar.DivarClient\/documentation\/Divar\/RawPlugEventType\/RPClickContactUs","doc:\/\/com.Divar.DivarClient\/documentation\/Divar\/RawPlugEventType\/RPClickDealershipContact","doc:\/\/com.Divar.DivarClient\/documentation\/Divar\/RawPlugEventType\/RPClickDealershipContactMethod","doc:\/\/com.Divar.DivarClient\/documentation\/Divar\/RawPlugEventType\/RPClickInspectionField","doc:\/\/com.Divar.DivarClient\/documentation\/Divar\/RawPlugEventType\/RPClickPost","doc:\/\/com.Divar.DivarClient\/documentation\/Divar\/RawPlugEventType\/RPClickRules","doc:\/\/com.Divar.DivarClient\/documentation\/Divar\/RawPlugEventType\/RPClickShare","doc:\/\/com.Divar.DivarClient\/documentation\/Divar\/RawPlugEventType\/RPClickSimilarBrandItem","doc:\/\/com.Divar.DivarClient\/documentation\/Divar\/RawPlugEventType\/RPClickSimilarPost","doc:\/\/com.Divar.DivarClient\/documentation\/Divar\/RawPlugEventType\/RPClickSubmitField","doc:\/\/com.Divar.DivarClient\/documentation\/Divar\/RawPlugEventType\/RPContactMethodDidSelect","doc:\/\/com.Divar.DivarClient\/documentation\/Divar\/RawPlugEventType\/RPDeletePostReason","doc:\/\/com.Divar.DivarClient\/documentation\/Divar\/RawPlugEventType\/RPDidEnterSubmit","doc:\/\/com.Divar.DivarClient\/documentation\/Divar\/RawPlugEventType\/RPDidExitSubmit","doc:\/\/com.Divar.DivarClient\/documentation\/Divar\/RawPlugEventType\/RPDivarDidInactive","doc:\/\/com.Divar.DivarClient\/documentation\/Divar\/RawPlugEventType\/RPDivarDidOpen","doc:\/\/com.Divar.DivarClient\/documentation\/Divar\/RawPlugEventType\/RPDivarDidReactive","doc:\/\/com.Divar.DivarClient\/documentation\/Divar\/RawPlugEventType\/RPEnterLogin","doc:\/\/com.Divar.DivarClient\/documentation\/Divar\/RawPlugEventType\/RPEnterVerificationCode","doc:\/\/com.Divar.DivarClient\/documentation\/Divar\/RawPlugEventType\/RPExtendPostDescriptionText","doc:\/\/com.Divar.DivarClient\/documentation\/Divar\/RawPlugEventType\/RPFeedBack","doc:\/\/com.Divar.DivarClient\/documentation\/Divar\/RawPlugEventType\/RPFilterDialogDidClose","doc:\/\/com.Divar.DivarClient\/documentation\/Divar\/RawPlugEventType\/RPFilterDidReset","doc:\/\/com.Divar.DivarClient\/documentation\/Divar\/RawPlugEventType\/RPFilterItemDidClear","doc:\/\/com.Divar.DivarClient\/documentation\/Divar\/RawPlugEventType\/RPFilterItemDidSelect","doc:\/\/com.Divar.DivarClient\/documentation\/Divar\/RawPlugEventType\/RPFiltersDidSelect","doc:\/\/com.Divar.DivarClient\/documentation\/Divar\/RawPlugEventType\/RPHistoryDidRemove","doc:\/\/com.Divar.DivarClient\/documentation\/Divar\/RawPlugEventType\/RPHistoryDidSelect","doc:\/\/com.Divar.DivarClient\/documentation\/Divar\/RawPlugEventType\/RPInputSuggestionDidSelect","doc:\/\/com.Divar.DivarClient\/documentation\/Divar\/RawPlugEventType\/RPInputSuggestionDidSubmit","doc:\/\/com.Divar.DivarClient\/documentation\/Divar\/RawPlugEventType\/RPListCategorySuggestion","doc:\/\/com.Divar.DivarClient\/documentation\/Divar\/RawPlugEventType\/RPLoadBrandPage","doc:\/\/com.Divar.DivarClient\/documentation\/Divar\/RawPlugEventType\/RPLoadFirstPage","doc:\/\/com.Divar.DivarClient\/documentation\/Divar\/RawPlugEventType\/RPLoadImage","doc:\/\/com.Divar.DivarClient\/documentation\/Divar\/RawPlugEventType\/RPLocationChangeCity","doc:\/\/com.Divar.DivarClient\/documentation\/Divar\/RawPlugEventType\/RPLocationChangeInMap","doc:\/\/com.Divar.DivarClient\/documentation\/Divar\/RawPlugEventType\/RPLocationChangeNeighbor","doc:\/\/com.Divar.DivarClient\/documentation\/Divar\/RawPlugEventType\/RPNewPostListPageDidLoad","doc:\/\/com.Divar.DivarClient\/documentation\/Divar\/RawPlugEventType\/RPOpenImagePreview","doc:\/\/com.Divar.DivarClient\/documentation\/Divar\/RawPlugEventType\/RPOtherFiltersDidSelect","doc:\/\/com.Divar.DivarClient\/documentation\/Divar\/RawPlugEventType\/RPOtherValuesDidSelect","doc:\/\/com.Divar.DivarClient\/documentation\/Divar\/RawPlugEventType\/RPPostContactDidShow","doc:\/\/com.Divar.DivarClient\/documentation\/Divar\/RawPlugEventType\/RPPostDidBookmarked","doc:\/\/com.Divar.DivarClient\/documentation\/Divar\/RawPlugEventType\/RPPostDidClose","doc:\/\/com.Divar.DivarClient\/documentation\/Divar\/RawPlugEventType\/RPPostNote","doc:\/\/com.Divar.DivarClient\/documentation\/Divar\/RawPlugEventType\/RPPostsListDidScroll","doc:\/\/com.Divar.DivarClient\/documentation\/Divar\/RawPlugEventType\/RPPreloadContactInfo","doc:\/\/com.Divar.DivarClient\/documentation\/Divar\/RawPlugEventType\/RPPreviewDidOpen","doc:\/\/com.Divar.DivarClient\/documentation\/Divar\/RawPlugEventType\/RPPreviewSimilarPosts","doc:\/\/com.Divar.DivarClient\/documentation\/Divar\/RawPlugEventType\/RPRecentDidRemoveFromList","doc:\/\/com.Divar.DivarClient\/documentation\/Divar\/RawPlugEventType\/RPRegisterDealership","doc:\/\/com.Divar.DivarClient\/documentation\/Divar\/RawPlugEventType\/RPSMSContactMethodStatus","doc:\/\/com.Divar.DivarClient\/documentation\/Divar\/RawPlugEventType\/RPSearchDidDone","doc:\/\/com.Divar.DivarClient\/documentation\/Divar\/RawPlugEventType\/RPSearchDidSelect","doc:\/\/com.Divar.DivarClient\/documentation\/Divar\/RawPlugEventType\/RPShowBlockedConversations","doc:\/\/com.Divar.DivarClient\/documentation\/Divar\/RawPlugEventType\/RPSmartSuggestionDidSelect","doc:\/\/com.Divar.DivarClient\/documentation\/Divar\/RawPlugEventType\/RPSubmitAddPhoto","doc:\/\/com.Divar.DivarClient\/documentation\/Divar\/RawPlugEventType\/RPSubmitNextPage","doc:\/\/com.Divar.DivarClient\/documentation\/Divar\/RawPlugEventType\/RPSubmitPostSaveLocation","doc:\/\/com.Divar.DivarClient\/documentation\/Divar\/RawPlugEventType\/RPSubmitPreviousPage","doc:\/\/com.Divar.DivarClient\/documentation\/Divar\/RawPlugEventType\/RPSubmitRemovePhoto","doc:\/\/com.Divar.DivarClient\/documentation\/Divar\/RawPlugEventType\/RPSubmitSelectCategory","doc:\/\/com.Divar.DivarClient\/documentation\/Divar\/RawPlugEventType\/RPSubmitVerificationCode","doc:\/\/com.Divar.DivarClient\/documentation\/Divar\/RawPlugEventType\/RPSuggestionDidSelect","doc:\/\/com.Divar.DivarClient\/documentation\/Divar\/RawPlugEventType\/RPTabDidChange","doc:\/\/com.Divar.DivarClient\/documentation\/Divar\/RawPlugEventType\/RPTitleDidSelect","doc:\/\/com.Divar.DivarClient\/documentation\/Divar\/RawPlugEventType\/RPValidationError","doc:\/\/com.Divar.DivarClient\/documentation\/Divar\/RawPlugEventType\/RPViewBulkLadder","doc:\/\/com.Divar.DivarClient\/documentation\/Divar\/RawPlugEventType\/RPViewDealershipManagmentPage","doc:\/\/com.Divar.DivarClient\/documentation\/Divar\/RawPlugEventType\/RPViewDealershipPage","doc:\/\/com.Divar.DivarClient\/documentation\/Divar\/RawPlugEventType\/RPViewInspectionReport","doc:\/\/com.Divar.DivarClient\/documentation\/Divar\/RawPlugEventType\/RPViewPaymentHistory","doc:\/\/com.Divar.DivarClient\/documentation\/Divar\/RawPlugEventType\/RPViewPostFeature","doc:\/\/com.Divar.DivarClient\/documentation\/Divar\/RawPlugEventType\/RPViewPriceReport","doc:\/\/com.Divar.DivarClient\/documentation\/Divar\/RawPlugEventType\/RPViewPurchaseSubscription","doc:\/\/com.Divar.DivarClient\/documentation\/Divar\/RawPlugEventType\/RPViewSubscriptionManagement","doc:\/\/com.Divar.DivarClient\/documentation\/Divar\/RawPlugEventType\/RegisterNextStep","doc:\/\/com.Divar.DivarClient\/documentation\/Divar\/RawPlugEventType\/RegisterPrevStep","doc:\/\/com.Divar.DivarClient\/documentation\/Divar\/RawPlugEventType\/SelectMultiConversationDelete","doc:\/\/com.Divar.DivarClient\/documentation\/Divar\/RawPlugEventType\/ShowCensoredLink","doc:\/\/com.Divar.DivarClient\/documentation\/Divar\/RawPlugEventType\/StartPayment","doc:\/\/com.Divar.DivarClient\/documentation\/Divar\/RawPlugEventType\/SwitchAccountType"]},{"title":"Initializers","identifiers":["doc:\/\/com.Divar.DivarClient\/documentation\/Divar\/RawPlugEventType\/init(rawValue:)"]},{"title":"Default Implementations","identifiers":["doc:\/\/com.Divar.DivarClient\/documentation\/Divar\/RawPlugEventType\/Equatable-Implementations","doc:\/\/com.Divar.DivarClient\/documentation\/Divar\/RawPlugEventType\/RawRepresentable-Implementations"],"generated":true}],"kind":"symbol","metadata":{"fragments":[{"kind":"keyword","text":"enum"},{"kind":"text","text":" "},{"kind":"identifier","text":"RawPlugEventType"}],"title":"RawPlugEventType","roleHeading":"Enumeration","role":"symbol","symbolKind":"enum","externalID":"s:5Divar16RawPlugEventTypeO","modules":[{"name":"Divar"}],"navigatorTitle":[{"kind":"identifier","text":"RawPlugEventType"}]},"hierarchy":{"paths":[["doc:\/\/com.Divar.DivarClient\/documentation\/Divar"]]},"references":{"doc://com.Divar.DivarClient/documentation/Divar/RawPlugEventType/RPViewBulkLadder":{"role":"symbol","title":"RawPlugEventType.RPViewBulkLadder","fragments":[{"kind":"keyword","text":"case"},{"kind":"text","text":" "},{"kind":"identifier","text":"RPViewBulkLadder"}],"abstract":[],"identifier":"doc:\/\/com.Divar.DivarClient\/documentation\/Divar\/RawPlugEventType\/RPViewBulkLadder","kind":"symbol","type":"topic","url":"\/documentation\/divar\/rawplugeventtype\/rpviewbulkladder"},"doc://com.Divar.DivarClient/documentation/Divar/RawPlugEventType/RPLocationChangeInMap":{"role":"symbol","title":"RawPlugEventType.RPLocationChangeInMap","fragments":[{"kind":"keyword","text":"case"},{"kind":"text","text":" "},{"kind":"identifier","text":"RPLocationChangeInMap"}],"abstract":[],"identifier":"doc:\/\/com.Divar.DivarClient\/documentation\/Divar\/RawPlugEventType\/RPLocationChangeInMap","kind":"symbol","type":"topic","url":"\/documentation\/divar\/rawplugeventtype\/rplocationchangeinmap"},"doc://com.Divar.DivarClient/documentation/Divar/RawPlugEventType/RPSubmitAddPhoto":{"role":"symbol","title":"RawPlugEventType.RPSubmitAddPhoto","fragments":[{"kind":"keyword","text":"case"},{"kind":"text","text":" "},{"kind":"identifier","text":"RPSubmitAddPhoto"}],"abstract":[],"identifier":"doc:\/\/com.Divar.DivarClient\/documentation\/Divar\/RawPlugEventType\/RPSubmitAddPhoto","kind":"symbol","type":"topic","url":"\/documentation\/divar\/rawplugeventtype\/rpsubmitaddphoto"},"doc://com.Divar.DivarClient/documentation/Divar/RawPlugEventType/RPExtendPostDescriptionText":{"role":"symbol","title":"RawPlugEventType.RPExtendPostDescriptionText","fragments":[{"kind":"keyword","text":"case"},{"kind":"text","text":" "},{"kind":"identifier","text":"RPExtendPostDescriptionText"}],"abstract":[],"identifier":"doc:\/\/com.Divar.DivarClient\/documentation\/Divar\/RawPlugEventType\/RPExtendPostDescriptionText","kind":"symbol","type":"topic","url":"\/documentation\/divar\/rawplugeventtype\/rpextendpostdescriptiontext"},"doc://com.Divar.DivarClient/documentation/Divar/RawPlugEventType/RPClickBaladPromotion":{"role":"symbol","title":"RawPlugEventType.RPClickBaladPromotion","fragments":[{"kind":"keyword","text":"case"},{"kind":"text","text":" "},{"kind":"identifier","text":"RPClickBaladPromotion"}],"abstract":[],"identifier":"doc:\/\/com.Divar.DivarClient\/documentation\/Divar\/RawPlugEventType\/RPClickBaladPromotion","kind":"symbol","type":"topic","url":"\/documentation\/divar\/rawplugeventtype\/rpclickbaladpromotion"},"doc://com.Divar.DivarClient/documentation/Divar/RawPlugEventType/RPInputSuggestionDidSubmit":{"role":"symbol","title":"RawPlugEventType.RPInputSuggestionDidSubmit","fragments":[{"kind":"keyword","text":"case"},{"kind":"text","text":" "},{"kind":"identifier","text":"RPInputSuggestionDidSubmit"}],"abstract":[],"identifier":"doc:\/\/com.Divar.DivarClient\/documentation\/Divar\/RawPlugEventType\/RPInputSuggestionDidSubmit","kind":"symbol","type":"topic","url":"\/documentation\/divar\/rawplugeventtype\/rpinputsuggestiondidsubmit"},"doc://com.Divar.DivarClient/documentation/Divar/RawPlugEventType/RPPostsListDidScroll":{"role":"symbol","title":"RawPlugEventType.RPPostsListDidScroll","fragments":[{"kind":"keyword","text":"case"},{"kind":"text","text":" "},{"kind":"identifier","text":"RPPostsListDidScroll"}],"abstract":[],"identifier":"doc:\/\/com.Divar.DivarClient\/documentation\/Divar\/RawPlugEventType\/RPPostsListDidScroll","kind":"symbol","type":"topic","url":"\/documentation\/divar\/rawplugeventtype\/rppostslistdidscroll"},"doc://com.Divar.DivarClient/documentation/Divar/RawPlugEventType/RPChatMessageEdit":{"role":"symbol","title":"RawPlugEventType.RPChatMessageEdit","fragments":[{"kind":"keyword","text":"case"},{"kind":"text","text":" "},{"kind":"identifier","text":"RPChatMessageEdit"}],"abstract":[],"identifier":"doc:\/\/com.Divar.DivarClient\/documentation\/Divar\/RawPlugEventType\/RPChatMessageEdit","kind":"symbol","type":"topic","url":"\/documentation\/divar\/rawplugeventtype\/rpchatmessageedit"},"doc://com.Divar.DivarClient/documentation/Divar/RawPlugEventType/RPLoadFirstPage":{"role":"symbol","title":"RawPlugEventType.RPLoadFirstPage","fragments":[{"kind":"keyword","text":"case"},{"kind":"text","text":" "},{"kind":"identifier","text":"RPLoadFirstPage"}],"abstract":[],"identifier":"doc:\/\/com.Divar.DivarClient\/documentation\/Divar\/RawPlugEventType\/RPLoadFirstPage","kind":"symbol","type":"topic","url":"\/documentation\/divar\/rawplugeventtype\/rploadfirstpage"},"doc://com.Divar.DivarClient/documentation/Divar/RawPlugEventType/RegisterPrevStep":{"role":"symbol","title":"RawPlugEventType.RegisterPrevStep","fragments":[{"kind":"keyword","text":"case"},{"kind":"text","text":" "},{"kind":"identifier","text":"RegisterPrevStep"}],"abstract":[],"identifier":"doc:\/\/com.Divar.DivarClient\/documentation\/Divar\/RawPlugEventType\/RegisterPrevStep","kind":"symbol","type":"topic","url":"\/documentation\/divar\/rawplugeventtype\/registerprevstep"},"doc://com.Divar.DivarClient/documentation/Divar/RawPlugEventType/RPSubmitPreviousPage":{"role":"symbol","title":"RawPlugEventType.RPSubmitPreviousPage","fragments":[{"kind":"keyword","text":"case"},{"kind":"text","text":" "},{"kind":"identifier","text":"RPSubmitPreviousPage"}],"abstract":[],"identifier":"doc:\/\/com.Divar.DivarClient\/documentation\/Divar\/RawPlugEventType\/RPSubmitPreviousPage","kind":"symbol","type":"topic","url":"\/documentation\/divar\/rawplugeventtype\/rpsubmitpreviouspage"},"doc://com.Divar.DivarClient/documentation/Divar/RawPlugEventType/RPSubmitSelectCategory":{"role":"symbol","title":"RawPlugEventType.RPSubmitSelectCategory","fragments":[{"kind":"keyword","text":"case"},{"kind":"text","text":" "},{"kind":"identifier","text":"RPSubmitSelectCategory"}],"abstract":[],"identifier":"doc:\/\/com.Divar.DivarClient\/documentation\/Divar\/RawPlugEventType\/RPSubmitSelectCategory","kind":"symbol","type":"topic","url":"\/documentation\/divar\/rawplugeventtype\/rpsubmitselectcategory"},"doc://com.Divar.DivarClient/documentation/Divar/RawPlugEventType/RPBulkLadderChoice":{"role":"symbol","title":"RawPlugEventType.RPBulkLadderChoice","fragments":[{"kind":"keyword","text":"case"},{"kind":"text","text":" "},{"kind":"identifier","text":"RPBulkLadderChoice"}],"abstract":[],"identifier":"doc:\/\/com.Divar.DivarClient\/documentation\/Divar\/RawPlugEventType\/RPBulkLadderChoice","kind":"symbol","type":"topic","url":"\/documentation\/divar\/rawplugeventtype\/rpbulkladderchoice"},"doc://com.Divar.DivarClient/documentation/Divar/RawPlugEventType/RPChatAttachmentDidSelect":{"role":"symbol","title":"RawPlugEventType.RPChatAttachmentDidSelect","fragments":[{"kind":"keyword","text":"case"},{"kind":"text","text":" "},{"kind":"identifier","text":"RPChatAttachmentDidSelect"}],"abstract":[],"identifier":"doc:\/\/com.Divar.DivarClient\/documentation\/Divar\/RawPlugEventType\/RPChatAttachmentDidSelect","kind":"symbol","type":"topic","url":"\/documentation\/divar\/rawplugeventtype\/rpchatattachmentdidselect"},"doc://com.Divar.DivarClient/documentation/Divar/RawPlugEventType/RPViewPriceReport":{"role":"symbol","title":"RawPlugEventType.RPViewPriceReport","fragments":[{"kind":"keyword","text":"case"},{"kind":"text","text":" "},{"kind":"identifier","text":"RPViewPriceReport"}],"abstract":[],"identifier":"doc:\/\/com.Divar.DivarClient\/documentation\/Divar\/RawPlugEventType\/RPViewPriceReport","kind":"symbol","type":"topic","url":"\/documentation\/divar\/rawplugeventtype\/rpviewpricereport"},"doc://com.Divar.DivarClient/documentation/Divar/RawPlugEventType/RPDivarDidReactive":{"role":"symbol","title":"RawPlugEventType.RPDivarDidReactive","fragments":[{"kind":"keyword","text":"case"},{"kind":"text","text":" "},{"kind":"identifier","text":"RPDivarDidReactive"}],"abstract":[],"identifier":"doc:\/\/com.Divar.DivarClient\/documentation\/Divar\/RawPlugEventType\/RPDivarDidReactive","kind":"symbol","type":"topic","url":"\/documentation\/divar\/rawplugeventtype\/rpdivardidreactive"},"doc://com.Divar.DivarClient/s8SendableP":{"type":"unresolvable","title":"Swift.Sendable","identifier":"doc:\/\/com.Divar.DivarClient\/s8SendableP"},"doc://com.Divar.DivarClient/documentation/Divar/RawPlugEventType/RPDivarDidInactive":{"role":"symbol","title":"RawPlugEventType.RPDivarDidInactive","fragments":[{"kind":"keyword","text":"case"},{"kind":"text","text":" "},{"kind":"identifier","text":"RPDivarDidInactive"}],"abstract":[],"identifier":"doc:\/\/com.Divar.DivarClient\/documentation\/Divar\/RawPlugEventType\/RPDivarDidInactive","kind":"symbol","type":"topic","url":"\/documentation\/divar\/rawplugeventtype\/rpdivardidinactive"},"doc://com.Divar.DivarClient/documentation/Divar/RawPlugEventType/RawRepresentable-Implementations":{"role":"collectionGroup","title":"RawRepresentable Implementations","abstract":[],"identifier":"doc:\/\/com.Divar.DivarClient\/documentation\/Divar\/RawPlugEventType\/RawRepresentable-Implementations","kind":"article","type":"topic","url":"\/documentation\/divar\/rawplugeventtype\/rawrepresentable-implementations"},"doc://com.Divar.DivarClient/documentation/Divar/RawPlugEventType/PostponeStep":{"role":"symbol","title":"RawPlugEventType.PostponeStep","fragments":[{"kind":"keyword","text":"case"},{"kind":"text","text":" "},{"kind":"identifier","text":"PostponeStep"}],"abstract":[],"identifier":"doc:\/\/com.Divar.DivarClient\/documentation\/Divar\/RawPlugEventType\/PostponeStep","kind":"symbol","type":"topic","url":"\/documentation\/divar\/rawplugeventtype\/postponestep"},"doc://com.Divar.DivarClient/documentation/Divar/RawPlugEventType/RPDeletePostReason":{"role":"symbol","title":"RawPlugEventType.RPDeletePostReason","fragments":[{"kind":"keyword","text":"case"},{"kind":"text","text":" "},{"kind":"identifier","text":"RPDeletePostReason"}],"abstract":[],"identifier":"doc:\/\/com.Divar.DivarClient\/documentation\/Divar\/RawPlugEventType\/RPDeletePostReason","kind":"symbol","type":"topic","url":"\/documentation\/divar\/rawplugeventtype\/rpdeletepostreason"},"doc://com.Divar.DivarClient/documentation/Divar/RawPlugEventType/RPViewDealershipPage":{"role":"symbol","title":"RawPlugEventType.RPViewDealershipPage","fragments":[{"kind":"keyword","text":"case"},{"kind":"text","text":" "},{"kind":"identifier","text":"RPViewDealershipPage"}],"abstract":[],"identifier":"doc:\/\/com.Divar.DivarClient\/documentation\/Divar\/RawPlugEventType\/RPViewDealershipPage","kind":"symbol","type":"topic","url":"\/documentation\/divar\/rawplugeventtype\/rpviewdealershippage"},"doc://com.Divar.DivarClient/documentation/Divar/RawPlugEventType/RPActionCatchDeepLink":{"role":"symbol","title":"RawPlugEventType.RPActionCatchDeepLink","fragments":[{"kind":"keyword","text":"case"},{"kind":"text","text":" "},{"kind":"identifier","text":"RPActionCatchDeepLink"}],"abstract":[],"identifier":"doc:\/\/com.Divar.DivarClient\/documentation\/Divar\/RawPlugEventType\/RPActionCatchDeepLink","kind":"symbol","type":"topic","url":"\/documentation\/divar\/rawplugeventtype\/rpactioncatchdeeplink"},"doc://com.Divar.DivarClient/documentation/Divar/RawPlugEventType/Notification":{"role":"symbol","title":"RawPlugEventType.Notification","fragments":[{"kind":"keyword","text":"case"},{"kind":"text","text":" "},{"kind":"identifier","text":"Notification"}],"abstract":[],"identifier":"doc:\/\/com.Divar.DivarClient\/documentation\/Divar\/RawPlugEventType\/Notification","kind":"symbol","type":"topic","url":"\/documentation\/divar\/rawplugeventtype\/notification"},"doc://com.Divar.DivarClient/documentation/Divar/RawPlugEventType/RPFeedBack":{"role":"symbol","title":"RawPlugEventType.RPFeedBack","fragments":[{"kind":"keyword","text":"case"},{"kind":"text","text":" "},{"kind":"identifier","text":"RPFeedBack"}],"abstract":[],"identifier":"doc:\/\/com.Divar.DivarClient\/documentation\/Divar\/RawPlugEventType\/RPFeedBack","kind":"symbol","type":"topic","url":"\/documentation\/divar\/rawplugeventtype\/rpfeedback"},"doc://com.Divar.DivarClient/documentation/Divar/RawPlugEventType/RPFilterItemDidSelect":{"role":"symbol","title":"RawPlugEventType.RPFilterItemDidSelect","fragments":[{"kind":"keyword","text":"case"},{"kind":"text","text":" "},{"kind":"identifier","text":"RPFilterItemDidSelect"}],"abstract":[],"identifier":"doc:\/\/com.Divar.DivarClient\/documentation\/Divar\/RawPlugEventType\/RPFilterItemDidSelect","kind":"symbol","type":"topic","url":"\/documentation\/divar\/rawplugeventtype\/rpfilteritemdidselect"},"doc://com.Divar.DivarClient/documentation/Divar/RawPlugEventType/RPCallInChatDidSelect":{"role":"symbol","title":"RawPlugEventType.RPCallInChatDidSelect","fragments":[{"kind":"keyword","text":"case"},{"kind":"text","text":" "},{"kind":"identifier","text":"RPCallInChatDidSelect"}],"abstract":[],"identifier":"doc:\/\/com.Divar.DivarClient\/documentation\/Divar\/RawPlugEventType\/RPCallInChatDidSelect","kind":"symbol","type":"topic","url":"\/documentation\/divar\/rawplugeventtype\/rpcallinchatdidselect"},"doc://com.Divar.DivarClient/documentation/Divar/RawPlugEventType/RPSMSContactMethodStatus":{"role":"symbol","title":"RawPlugEventType.RPSMSContactMethodStatus","fragments":[{"kind":"keyword","text":"case"},{"kind":"text","text":" "},{"kind":"identifier","text":"RPSMSContactMethodStatus"}],"abstract":[],"identifier":"doc:\/\/com.Divar.DivarClient\/documentation\/Divar\/RawPlugEventType\/RPSMSContactMethodStatus","kind":"symbol","type":"topic","url":"\/documentation\/divar\/rawplugeventtype\/rpsmscontactmethodstatus"},"doc://com.Divar.DivarClient/documentation/Divar/RawPlugEventType/RPPostDidClose":{"role":"symbol","title":"RawPlugEventType.RPPostDidClose","fragments":[{"kind":"keyword","text":"case"},{"kind":"text","text":" "},{"kind":"identifier","text":"RPPostDidClose"}],"abstract":[],"identifier":"doc:\/\/com.Divar.DivarClient\/documentation\/Divar\/RawPlugEventType\/RPPostDidClose","kind":"symbol","type":"topic","url":"\/documentation\/divar\/rawplugeventtype\/rppostdidclose"},"doc://com.Divar.DivarClient/documentation/Divar/RawPlugEventType/RPCategoryItemDidSelect":{"role":"symbol","title":"RawPlugEventType.RPCategoryItemDidSelect","fragments":[{"kind":"keyword","text":"case"},{"kind":"text","text":" "},{"kind":"identifier","text":"RPCategoryItemDidSelect"}],"abstract":[],"identifier":"doc:\/\/com.Divar.DivarClient\/documentation\/Divar\/RawPlugEventType\/RPCategoryItemDidSelect","kind":"symbol","type":"topic","url":"\/documentation\/divar\/rawplugeventtype\/rpcategoryitemdidselect"},"doc://com.Divar.DivarClient/documentation/Divar/RawPlugEventType/RPChatVoiceMessage":{"role":"symbol","title":"RawPlugEventType.RPChatVoiceMessage","fragments":[{"kind":"keyword","text":"case"},{"kind":"text","text":" "},{"kind":"identifier","text":"RPChatVoiceMessage"}],"abstract":[],"identifier":"doc:\/\/com.Divar.DivarClient\/documentation\/Divar\/RawPlugEventType\/RPChatVoiceMessage","kind":"symbol","type":"topic","url":"\/documentation\/divar\/rawplugeventtype\/rpchatvoicemessage"},"doc://com.Divar.DivarClient/documentation/Divar/RawPlugEventType/RPBookmarkDidRemoveFromList":{"role":"symbol","title":"RawPlugEventType.RPBookmarkDidRemoveFromList","fragments":[{"kind":"keyword","text":"case"},{"kind":"text","text":" "},{"kind":"identifier","text":"RPBookmarkDidRemoveFromList"}],"abstract":[],"identifier":"doc:\/\/com.Divar.DivarClient\/documentation\/Divar\/RawPlugEventType\/RPBookmarkDidRemoveFromList","kind":"symbol","type":"topic","url":"\/documentation\/divar\/rawplugeventtype\/rpbookmarkdidremovefromlist"},"doc://com.Divar.DivarClient/documentation/Divar/RawPlugEventType/init(rawValue:)":{"role":"symbol","title":"init(rawValue:)","fragments":[{"kind":"identifier","text":"init"},{"kind":"text","text":"?("},{"kind":"externalParam","text":"rawValue"},{"kind":"text","text":": "},{"kind":"typeIdentifier","text":"String","preciseIdentifier":"s:SS"},{"kind":"text","text":")"}],"abstract":[],"identifier":"doc:\/\/com.Divar.DivarClient\/documentation\/Divar\/RawPlugEventType\/init(rawValue:)","kind":"symbol","type":"topic","url":"\/documentation\/divar\/rawplugeventtype\/init(rawvalue:)"},"doc://com.Divar.DivarClient/documentation/Divar/RawPlugEventType/RPPostContactDidShow":{"role":"symbol","title":"RawPlugEventType.RPPostContactDidShow","fragments":[{"kind":"keyword","text":"case"},{"kind":"text","text":" "},{"kind":"identifier","text":"RPPostContactDidShow"}],"abstract":[],"identifier":"doc:\/\/com.Divar.DivarClient\/documentation\/Divar\/RawPlugEventType\/RPPostContactDidShow","kind":"symbol","type":"topic","url":"\/documentation\/divar\/rawplugeventtype\/rppostcontactdidshow"},"doc://com.Divar.DivarClient/documentation/Divar/RawPlugEventType/StartPayment":{"role":"symbol","title":"RawPlugEventType.StartPayment","fragments":[{"kind":"keyword","text":"case"},{"kind":"text","text":" "},{"kind":"identifier","text":"StartPayment"}],"abstract":[],"identifier":"doc:\/\/com.Divar.DivarClient\/documentation\/Divar\/RawPlugEventType\/StartPayment","kind":"symbol","type":"topic","url":"\/documentation\/divar\/rawplugeventtype\/startpayment"},"doc://com.Divar.DivarClient/documentation/Divar/RawPlugEventType/RPValidationError":{"role":"symbol","title":"RawPlugEventType.RPValidationError","fragments":[{"kind":"keyword","text":"case"},{"kind":"text","text":" "},{"kind":"identifier","text":"RPValidationError"}],"abstract":[],"identifier":"doc:\/\/com.Divar.DivarClient\/documentation\/Divar\/RawPlugEventType\/RPValidationError","kind":"symbol","type":"topic","url":"\/documentation\/divar\/rawplugeventtype\/rpvalidationerror"},"doc://com.Divar.DivarClient/documentation/Divar/RawPlugEventType/SwitchAccountType":{"role":"symbol","title":"RawPlugEventType.SwitchAccountType","fragments":[{"kind":"keyword","text":"case"},{"kind":"text","text":" "},{"kind":"identifier","text":"SwitchAccountType"}],"abstract":[],"identifier":"doc:\/\/com.Divar.DivarClient\/documentation\/Divar\/RawPlugEventType\/SwitchAccountType","kind":"symbol","type":"topic","url":"\/documentation\/divar\/rawplugeventtype\/switchaccounttype"},"doc://com.Divar.DivarClient/documentation/Divar/RawPlugEventType/DeleteConversations":{"role":"symbol","title":"RawPlugEventType.DeleteConversations","fragments":[{"kind":"keyword","text":"case"},{"kind":"text","text":" "},{"kind":"identifier","text":"DeleteConversations"}],"abstract":[],"identifier":"doc:\/\/com.Divar.DivarClient\/documentation\/Divar\/RawPlugEventType\/DeleteConversations","kind":"symbol","type":"topic","url":"\/documentation\/divar\/rawplugeventtype\/deleteconversations"},"doc://com.Divar.DivarClient/documentation/Divar/RawPlugEventType/RPViewPaymentHistory":{"role":"symbol","title":"RawPlugEventType.RPViewPaymentHistory","fragments":[{"kind":"keyword","text":"case"},{"kind":"text","text":" "},{"kind":"identifier","text":"RPViewPaymentHistory"}],"abstract":[],"identifier":"doc:\/\/com.Divar.DivarClient\/documentation\/Divar\/RawPlugEventType\/RPViewPaymentHistory","kind":"symbol","type":"topic","url":"\/documentation\/divar\/rawplugeventtype\/rpviewpaymenthistory"},"doc://com.Divar.DivarClient/documentation/Divar/RawPlugEventType/RPClickInspectionField":{"role":"symbol","title":"RawPlugEventType.RPClickInspectionField","fragments":[{"kind":"keyword","text":"case"},{"kind":"text","text":" "},{"kind":"identifier","text":"RPClickInspectionField"}],"abstract":[],"identifier":"doc:\/\/com.Divar.DivarClient\/documentation\/Divar\/RawPlugEventType\/RPClickInspectionField","kind":"symbol","type":"topic","url":"\/documentation\/divar\/rawplugeventtype\/rpclickinspectionfield"},"doc://com.Divar.DivarClient/documentation/Divar/RawPlugEventType/RPChatReportSpamDidSelect":{"role":"symbol","title":"RawPlugEventType.RPChatReportSpamDidSelect","fragments":[{"kind":"keyword","text":"case"},{"kind":"text","text":" "},{"kind":"identifier","text":"RPChatReportSpamDidSelect"}],"abstract":[],"identifier":"doc:\/\/com.Divar.DivarClient\/documentation\/Divar\/RawPlugEventType\/RPChatReportSpamDidSelect","kind":"symbol","type":"topic","url":"\/documentation\/divar\/rawplugeventtype\/rpchatreportspamdidselect"},"doc://com.Divar.DivarClient/documentation/Divar/RawPlugEventType/RPFilterDidReset":{"role":"symbol","title":"RawPlugEventType.RPFilterDidReset","fragments":[{"kind":"keyword","text":"case"},{"kind":"text","text":" "},{"kind":"identifier","text":"RPFilterDidReset"}],"abstract":[],"identifier":"doc:\/\/com.Divar.DivarClient\/documentation\/Divar\/RawPlugEventType\/RPFilterDidReset","kind":"symbol","type":"topic","url":"\/documentation\/divar\/rawplugeventtype\/rpfilterdidreset"},"doc://com.Divar.DivarClient/documentation/Divar/RawPlugEventType/RPPreloadContactInfo":{"role":"symbol","title":"RawPlugEventType.RPPreloadContactInfo","fragments":[{"kind":"keyword","text":"case"},{"kind":"text","text":" "},{"kind":"identifier","text":"RPPreloadContactInfo"}],"abstract":[],"identifier":"doc:\/\/com.Divar.DivarClient\/documentation\/Divar\/RawPlugEventType\/RPPreloadContactInfo","kind":"symbol","type":"topic","url":"\/documentation\/divar\/rawplugeventtype\/rppreloadcontactinfo"},"doc://com.Divar.DivarClient/SY":{"type":"unresolvable","title":"Swift.RawRepresentable","identifier":"doc:\/\/com.Divar.DivarClient\/SY"},"doc://com.Divar.DivarClient/documentation/Divar/RawPlugEventType/RPSearchDidSelect":{"role":"symbol","title":"RawPlugEventType.RPSearchDidSelect","fragments":[{"kind":"keyword","text":"case"},{"kind":"text","text":" "},{"kind":"identifier","text":"RPSearchDidSelect"}],"abstract":[],"identifier":"doc:\/\/com.Divar.DivarClient\/documentation\/Divar\/RawPlugEventType\/RPSearchDidSelect","kind":"symbol","type":"topic","url":"\/documentation\/divar\/rawplugeventtype\/rpsearchdidselect"},"doc://com.Divar.DivarClient/documentation/Divar/RawPlugEventType/RPBack":{"role":"symbol","title":"RawPlugEventType.RPBack","fragments":[{"kind":"keyword","text":"case"},{"kind":"text","text":" "},{"kind":"identifier","text":"RPBack"}],"abstract":[],"identifier":"doc:\/\/com.Divar.DivarClient\/documentation\/Divar\/RawPlugEventType\/RPBack","kind":"symbol","type":"topic","url":"\/documentation\/divar\/rawplugeventtype\/rpback"},"doc://com.Divar.DivarClient/documentation/Divar/RawPlugEventType/RPClickBrandPosts":{"role":"symbol","title":"RawPlugEventType.RPClickBrandPosts","fragments":[{"kind":"keyword","text":"case"},{"kind":"text","text":" "},{"kind":"identifier","text":"RPClickBrandPosts"}],"abstract":[],"identifier":"doc:\/\/com.Divar.DivarClient\/documentation\/Divar\/RawPlugEventType\/RPClickBrandPosts","kind":"symbol","type":"topic","url":"\/documentation\/divar\/rawplugeventtype\/rpclickbrandposts"},"doc://com.Divar.DivarClient/documentation/Divar/RawPlugEventType/PromotePostPlan":{"role":"symbol","title":"RawPlugEventType.PromotePostPlan","fragments":[{"kind":"keyword","text":"case"},{"kind":"text","text":" "},{"kind":"identifier","text":"PromotePostPlan"}],"abstract":[],"identifier":"doc:\/\/com.Divar.DivarClient\/documentation\/Divar\/RawPlugEventType\/PromotePostPlan","kind":"symbol","type":"topic","url":"\/documentation\/divar\/rawplugeventtype\/promotepostplan"},"doc://com.Divar.DivarClient/documentation/Divar/RawPlugEventType/RPClickContactUs":{"role":"symbol","title":"RawPlugEventType.RPClickContactUs","fragments":[{"kind":"keyword","text":"case"},{"kind":"text","text":" "},{"kind":"identifier","text":"RPClickContactUs"}],"abstract":[],"identifier":"doc:\/\/com.Divar.DivarClient\/documentation\/Divar\/RawPlugEventType\/RPClickContactUs","kind":"symbol","type":"topic","url":"\/documentation\/divar\/rawplugeventtype\/rpclickcontactus"},"doc://com.Divar.DivarClient/documentation/Divar/RawPlugEventType/RegisterNextStep":{"role":"symbol","title":"RawPlugEventType.RegisterNextStep","fragments":[{"kind":"keyword","text":"case"},{"kind":"text","text":" "},{"kind":"identifier","text":"RegisterNextStep"}],"abstract":[],"identifier":"doc:\/\/com.Divar.DivarClient\/documentation\/Divar\/RawPlugEventType\/RegisterNextStep","kind":"symbol","type":"topic","url":"\/documentation\/divar\/rawplugeventtype\/registernextstep"},"doc://com.Divar.DivarClient/documentation/Divar":{"role":"collection","title":"Divar","abstract":[],"identifier":"doc:\/\/com.Divar.DivarClient\/documentation\/Divar","kind":"symbol","type":"topic","url":"\/documentation\/divar"},"doc://com.Divar.DivarClient/documentation/Divar/RawPlugEventType/RPClickShare":{"role":"symbol","title":"RawPlugEventType.RPClickShare","fragments":[{"kind":"keyword","text":"case"},{"kind":"text","text":" "},{"kind":"identifier","text":"RPClickShare"}],"abstract":[],"identifier":"doc:\/\/com.Divar.DivarClient\/documentation\/Divar\/RawPlugEventType\/RPClickShare","kind":"symbol","type":"topic","url":"\/documentation\/divar\/rawplugeventtype\/rpclickshare"},"doc://com.Divar.DivarClient/documentation/Divar/RawPlugEventType/RPViewPostFeature":{"role":"symbol","title":"RawPlugEventType.RPViewPostFeature","fragments":[{"kind":"keyword","text":"case"},{"kind":"text","text":" "},{"kind":"identifier","text":"RPViewPostFeature"}],"abstract":[],"identifier":"doc:\/\/com.Divar.DivarClient\/documentation\/Divar\/RawPlugEventType\/RPViewPostFeature","kind":"symbol","type":"topic","url":"\/documentation\/divar\/rawplugeventtype\/rpviewpostfeature"},"doc://com.Divar.DivarClient/documentation/Divar/RawPlugEventType/RPRecentDidRemoveFromList":{"role":"symbol","title":"RawPlugEventType.RPRecentDidRemoveFromList","fragments":[{"kind":"keyword","text":"case"},{"kind":"text","text":" "},{"kind":"identifier","text":"RPRecentDidRemoveFromList"}],"abstract":[],"identifier":"doc:\/\/com.Divar.DivarClient\/documentation\/Divar\/RawPlugEventType\/RPRecentDidRemoveFromList","kind":"symbol","type":"topic","url":"\/documentation\/divar\/rawplugeventtype\/rprecentdidremovefromlist"},"doc://com.Divar.DivarClient/documentation/Divar/RawPlugEventType/RPClickDealershipContactMethod":{"role":"symbol","title":"RawPlugEventType.RPClickDealershipContactMethod","fragments":[{"kind":"keyword","text":"case"},{"kind":"text","text":" "},{"kind":"identifier","text":"RPClickDealershipContactMethod"}],"abstract":[],"identifier":"doc:\/\/com.Divar.DivarClient\/documentation\/Divar\/RawPlugEventType\/RPClickDealershipContactMethod","kind":"symbol","type":"topic","url":"\/documentation\/divar\/rawplugeventtype\/rpclickdealershipcontactmethod"},"doc://com.Divar.DivarClient/documentation/Divar/RawPlugEventType/Decline":{"role":"symbol","title":"RawPlugEventType.Decline","fragments":[{"kind":"keyword","text":"case"},{"kind":"text","text":" "},{"kind":"identifier","text":"Decline"}],"abstract":[],"identifier":"doc:\/\/com.Divar.DivarClient\/documentation\/Divar\/RawPlugEventType\/Decline","kind":"symbol","type":"topic","url":"\/documentation\/divar\/rawplugeventtype\/decline"},"doc://com.Divar.DivarClient/documentation/Divar/RawPlugEventType/RPPostNote":{"role":"symbol","title":"RawPlugEventType.RPPostNote","fragments":[{"kind":"keyword","text":"case"},{"kind":"text","text":" "},{"kind":"identifier","text":"RPPostNote"}],"abstract":[],"identifier":"doc:\/\/com.Divar.DivarClient\/documentation\/Divar\/RawPlugEventType\/RPPostNote","kind":"symbol","type":"topic","url":"\/documentation\/divar\/rawplugeventtype\/rppostnote"},"doc://com.Divar.DivarClient/documentation/Divar/RawPlugEventType/RPClickSubmitField":{"role":"symbol","title":"RawPlugEventType.RPClickSubmitField","fragments":[{"kind":"keyword","text":"case"},{"kind":"text","text":" "},{"kind":"identifier","text":"RPClickSubmitField"}],"abstract":[],"identifier":"doc:\/\/com.Divar.DivarClient\/documentation\/Divar\/RawPlugEventType\/RPClickSubmitField","kind":"symbol","type":"topic","url":"\/documentation\/divar\/rawplugeventtype\/rpclicksubmitfield"},"doc://com.Divar.DivarClient/documentation/Divar/RawPlugEventType/RPChatSuggestionMessage":{"role":"symbol","title":"RawPlugEventType.RPChatSuggestionMessage","fragments":[{"kind":"keyword","text":"case"},{"kind":"text","text":" "},{"kind":"identifier","text":"RPChatSuggestionMessage"}],"abstract":[],"identifier":"doc:\/\/com.Divar.DivarClient\/documentation\/Divar\/RawPlugEventType\/RPChatSuggestionMessage","kind":"symbol","type":"topic","url":"\/documentation\/divar\/rawplugeventtype\/rpchatsuggestionmessage"},"doc://com.Divar.DivarClient/documentation/Divar/RawPlugEventType/RPInputSuggestionDidSelect":{"role":"symbol","title":"RawPlugEventType.RPInputSuggestionDidSelect","fragments":[{"kind":"keyword","text":"case"},{"kind":"text","text":" "},{"kind":"identifier","text":"RPInputSuggestionDidSelect"}],"abstract":[],"identifier":"doc:\/\/com.Divar.DivarClient\/documentation\/Divar\/RawPlugEventType\/RPInputSuggestionDidSelect","kind":"symbol","type":"topic","url":"\/documentation\/divar\/rawplugeventtype\/rpinputsuggestiondidselect"},"doc://com.Divar.DivarClient/documentation/Divar/RawPlugEventType/RPClickDealershipContact":{"role":"symbol","title":"RawPlugEventType.RPClickDealershipContact","fragments":[{"kind":"keyword","text":"case"},{"kind":"text","text":" "},{"kind":"identifier","text":"RPClickDealershipContact"}],"abstract":[],"identifier":"doc:\/\/com.Divar.DivarClient\/documentation\/Divar\/RawPlugEventType\/RPClickDealershipContact","kind":"symbol","type":"topic","url":"\/documentation\/divar\/rawplugeventtype\/rpclickdealershipcontact"},"doc://com.Divar.DivarClient/documentation/Divar/RawPlugEventType/RPLoadBrandPage":{"role":"symbol","title":"RawPlugEventType.RPLoadBrandPage","fragments":[{"kind":"keyword","text":"case"},{"kind":"text","text":" "},{"kind":"identifier","text":"RPLoadBrandPage"}],"abstract":[],"identifier":"doc:\/\/com.Divar.DivarClient\/documentation\/Divar\/RawPlugEventType\/RPLoadBrandPage","kind":"symbol","type":"topic","url":"\/documentation\/divar\/rawplugeventtype\/rploadbrandpage"},"doc://com.Divar.DivarClient/documentation/Divar/RawPlugEventType/RPActionVoipInit":{"role":"symbol","title":"RawPlugEventType.RPActionVoipInit","fragments":[{"kind":"keyword","text":"case"},{"kind":"text","text":" "},{"kind":"identifier","text":"RPActionVoipInit"}],"abstract":[],"identifier":"doc:\/\/com.Divar.DivarClient\/documentation\/Divar\/RawPlugEventType\/RPActionVoipInit","kind":"symbol","type":"topic","url":"\/documentation\/divar\/rawplugeventtype\/rpactionvoipinit"},"doc://com.Divar.DivarClient/documentation/Divar/RawPlugEventType/RPChooseMap":{"role":"symbol","title":"RawPlugEventType.RPChooseMap","fragments":[{"kind":"keyword","text":"case"},{"kind":"text","text":" "},{"kind":"identifier","text":"RPChooseMap"}],"abstract":[],"identifier":"doc:\/\/com.Divar.DivarClient\/documentation\/Divar\/RawPlugEventType\/RPChooseMap","kind":"symbol","type":"topic","url":"\/documentation\/divar\/rawplugeventtype\/rpchoosemap"},"doc://com.Divar.DivarClient/documentation/Divar/RawPlugEventType/RPShowBlockedConversations":{"role":"symbol","title":"RawPlugEventType.RPShowBlockedConversations","fragments":[{"kind":"keyword","text":"case"},{"kind":"text","text":" "},{"kind":"identifier","text":"RPShowBlockedConversations"}],"abstract":[],"identifier":"doc:\/\/com.Divar.DivarClient\/documentation\/Divar\/RawPlugEventType\/RPShowBlockedConversations","kind":"symbol","type":"topic","url":"\/documentation\/divar\/rawplugeventtype\/rpshowblockedconversations"},"doc://com.Divar.DivarClient/documentation/Divar/RawPlugEventType/RPSmartSuggestionDidSelect":{"role":"symbol","title":"RawPlugEventType.RPSmartSuggestionDidSelect","fragments":[{"kind":"keyword","text":"case"},{"kind":"text","text":" "},{"kind":"identifier","text":"RPSmartSuggestionDidSelect"}],"abstract":[],"identifier":"doc:\/\/com.Divar.DivarClient\/documentation\/Divar\/RawPlugEventType\/RPSmartSuggestionDidSelect","kind":"symbol","type":"topic","url":"\/documentation\/divar\/rawplugeventtype\/rpsmartsuggestiondidselect"},"doc://com.Divar.DivarClient/documentation/Divar/RawPlugEventType/RPClickRules":{"role":"symbol","title":"RawPlugEventType.RPClickRules","fragments":[{"kind":"keyword","text":"case"},{"kind":"text","text":" "},{"kind":"identifier","text":"RPClickRules"}],"abstract":[],"identifier":"doc:\/\/com.Divar.DivarClient\/documentation\/Divar\/RawPlugEventType\/RPClickRules","kind":"symbol","type":"topic","url":"\/documentation\/divar\/rawplugeventtype\/rpclickrules"},"doc://com.Divar.DivarClient/documentation/Divar/RawPlugEventType/RPTabDidChange":{"role":"symbol","title":"RawPlugEventType.RPTabDidChange","fragments":[{"kind":"keyword","text":"case"},{"kind":"text","text":" "},{"kind":"identifier","text":"RPTabDidChange"}],"abstract":[],"identifier":"doc:\/\/com.Divar.DivarClient\/documentation\/Divar\/RawPlugEventType\/RPTabDidChange","kind":"symbol","type":"topic","url":"\/documentation\/divar\/rawplugeventtype\/rptabdidchange"},"doc://com.Divar.DivarClient/documentation/Divar/RawPlugEventType/RPClickSimilarBrandItem":{"role":"symbol","title":"RawPlugEventType.RPClickSimilarBrandItem","fragments":[{"kind":"keyword","text":"case"},{"kind":"text","text":" "},{"kind":"identifier","text":"RPClickSimilarBrandItem"}],"abstract":[],"identifier":"doc:\/\/com.Divar.DivarClient\/documentation\/Divar\/RawPlugEventType\/RPClickSimilarBrandItem","kind":"symbol","type":"topic","url":"\/documentation\/divar\/rawplugeventtype\/rpclicksimilarbranditem"},"doc://com.Divar.DivarClient/documentation/Divar/RawPlugEventType/RPPreviewDidOpen":{"role":"symbol","title":"RawPlugEventType.RPPreviewDidOpen","fragments":[{"kind":"keyword","text":"case"},{"kind":"text","text":" "},{"kind":"identifier","text":"RPPreviewDidOpen"}],"abstract":[],"identifier":"doc:\/\/com.Divar.DivarClient\/documentation\/Divar\/RawPlugEventType\/RPPreviewDidOpen","kind":"symbol","type":"topic","url":"\/documentation\/divar\/rawplugeventtype\/rppreviewdidopen"},"doc://com.Divar.DivarClient/documentation/Divar/RawPlugEventType/RPEnterVerificationCode":{"role":"symbol","title":"RawPlugEventType.RPEnterVerificationCode","fragments":[{"kind":"keyword","text":"case"},{"kind":"text","text":" "},{"kind":"identifier","text":"RPEnterVerificationCode"}],"abstract":[],"identifier":"doc:\/\/com.Divar.DivarClient\/documentation\/Divar\/RawPlugEventType\/RPEnterVerificationCode","kind":"symbol","type":"topic","url":"\/documentation\/divar\/rawplugeventtype\/rpenterverificationcode"},"doc://com.Divar.DivarClient/documentation/Divar/RawPlugEventType/RPClickPost":{"role":"symbol","title":"RawPlugEventType.RPClickPost","fragments":[{"kind":"keyword","text":"case"},{"kind":"text","text":" "},{"kind":"identifier","text":"RPClickPost"}],"abstract":[],"identifier":"doc:\/\/com.Divar.DivarClient\/documentation\/Divar\/RawPlugEventType\/RPClickPost","kind":"symbol","type":"topic","url":"\/documentation\/divar\/rawplugeventtype\/rpclickpost"},"doc://com.Divar.DivarClient/documentation/Divar/RawPlugEventType/RPEnterLogin":{"role":"symbol","title":"RawPlugEventType.RPEnterLogin","fragments":[{"kind":"keyword","text":"case"},{"kind":"text","text":" "},{"kind":"identifier","text":"RPEnterLogin"}],"abstract":[],"identifier":"doc:\/\/com.Divar.DivarClient\/documentation\/Divar\/RawPlugEventType\/RPEnterLogin","kind":"symbol","type":"topic","url":"\/documentation\/divar\/rawplugeventtype\/rpenterlogin"},"doc://com.Divar.DivarClient/documentation/Divar/RawPlugEventType/RPFiltersDidSelect":{"role":"symbol","title":"RawPlugEventType.RPFiltersDidSelect","fragments":[{"kind":"keyword","text":"case"},{"kind":"text","text":" "},{"kind":"identifier","text":"RPFiltersDidSelect"}],"abstract":[],"identifier":"doc:\/\/com.Divar.DivarClient\/documentation\/Divar\/RawPlugEventType\/RPFiltersDidSelect","kind":"symbol","type":"topic","url":"\/documentation\/divar\/rawplugeventtype\/rpfiltersdidselect"},"doc://com.Divar.DivarClient/documentation/Divar/RawPlugEventType/RPActionVoipReady":{"role":"symbol","title":"RawPlugEventType.RPActionVoipReady","fragments":[{"kind":"keyword","text":"case"},{"kind":"text","text":" "},{"kind":"identifier","text":"RPActionVoipReady"}],"abstract":[],"identifier":"doc:\/\/com.Divar.DivarClient\/documentation\/Divar\/RawPlugEventType\/RPActionVoipReady","kind":"symbol","type":"topic","url":"\/documentation\/divar\/rawplugeventtype\/rpactionvoipready"},"doc://com.Divar.DivarClient/documentation/Divar/RawPlugEventType/RPViewSubscriptionManagement":{"role":"symbol","title":"RawPlugEventType.RPViewSubscriptionManagement","fragments":[{"kind":"keyword","text":"case"},{"kind":"text","text":" "},{"kind":"identifier","text":"RPViewSubscriptionManagement"}],"abstract":[],"identifier":"doc:\/\/com.Divar.DivarClient\/documentation\/Divar\/RawPlugEventType\/RPViewSubscriptionManagement","kind":"symbol","type":"topic","url":"\/documentation\/divar\/rawplugeventtype\/rpviewsubscriptionmanagement"},"doc://com.Divar.DivarClient/documentation/Divar/RawPlugEventType/SelectMultiConversationDelete":{"role":"symbol","title":"RawPlugEventType.SelectMultiConversationDelete","fragments":[{"kind":"keyword","text":"case"},{"kind":"text","text":" "},{"kind":"identifier","text":"SelectMultiConversationDelete"}],"abstract":[],"identifier":"doc:\/\/com.Divar.DivarClient\/documentation\/Divar\/RawPlugEventType\/SelectMultiConversationDelete","kind":"symbol","type":"topic","url":"\/documentation\/divar\/rawplugeventtype\/selectmulticonversationdelete"},"doc://com.Divar.DivarClient/documentation/Divar/RawPlugEventType/RPChatIsTyping":{"role":"symbol","title":"RawPlugEventType.RPChatIsTyping","fragments":[{"kind":"keyword","text":"case"},{"kind":"text","text":" "},{"kind":"identifier","text":"RPChatIsTyping"}],"abstract":[],"identifier":"doc:\/\/com.Divar.DivarClient\/documentation\/Divar\/RawPlugEventType\/RPChatIsTyping","kind":"symbol","type":"topic","url":"\/documentation\/divar\/rawplugeventtype\/rpchatistyping"},"doc://com.Divar.DivarClient/documentation/Divar/RawPlugEventType/RPViewPurchaseSubscription":{"role":"symbol","title":"RawPlugEventType.RPViewPurchaseSubscription","fragments":[{"kind":"keyword","text":"case"},{"kind":"text","text":" "},{"kind":"identifier","text":"RPViewPurchaseSubscription"}],"abstract":[],"identifier":"doc:\/\/com.Divar.DivarClient\/documentation\/Divar\/RawPlugEventType\/RPViewPurchaseSubscription","kind":"symbol","type":"topic","url":"\/documentation\/divar\/rawplugeventtype\/rpviewpurchasesubscription"},"doc://com.Divar.DivarClient/documentation/Divar/RawPlugEventType/RPDidExitSubmit":{"role":"symbol","title":"RawPlugEventType.RPDidExitSubmit","fragments":[{"kind":"keyword","text":"case"},{"kind":"text","text":" "},{"kind":"identifier","text":"RPDidExitSubmit"}],"abstract":[],"identifier":"doc:\/\/com.Divar.DivarClient\/documentation\/Divar\/RawPlugEventType\/RPDidExitSubmit","kind":"symbol","type":"topic","url":"\/documentation\/divar\/rawplugeventtype\/rpdidexitsubmit"},"doc://com.Divar.DivarClient/documentation/Divar/RawPlugEventType/RPDidEnterSubmit":{"role":"symbol","title":"RawPlugEventType.RPDidEnterSubmit","fragments":[{"kind":"keyword","text":"case"},{"kind":"text","text":" "},{"kind":"identifier","text":"RPDidEnterSubmit"}],"abstract":[],"identifier":"doc:\/\/com.Divar.DivarClient\/documentation\/Divar\/RawPlugEventType\/RPDidEnterSubmit","kind":"symbol","type":"topic","url":"\/documentation\/divar\/rawplugeventtype\/rpdidentersubmit"},"doc://com.Divar.DivarClient/documentation/Divar/RawPlugEventType/RPHistoryDidRemove":{"role":"symbol","title":"RawPlugEventType.RPHistoryDidRemove","fragments":[{"kind":"keyword","text":"case"},{"kind":"text","text":" "},{"kind":"identifier","text":"RPHistoryDidRemove"}],"abstract":[],"identifier":"doc:\/\/com.Divar.DivarClient\/documentation\/Divar\/RawPlugEventType\/RPHistoryDidRemove","kind":"symbol","type":"topic","url":"\/documentation\/divar\/rawplugeventtype\/rphistorydidremove"},"doc://com.Divar.DivarClient/documentation/Divar/RawPlugEventType/RPTitleDidSelect":{"role":"symbol","title":"RawPlugEventType.RPTitleDidSelect","fragments":[{"kind":"keyword","text":"case"},{"kind":"text","text":" "},{"kind":"identifier","text":"RPTitleDidSelect"}],"abstract":[],"identifier":"doc:\/\/com.Divar.DivarClient\/documentation\/Divar\/RawPlugEventType\/RPTitleDidSelect","kind":"symbol","type":"topic","url":"\/documentation\/divar\/rawplugeventtype\/rptitledidselect"},"doc://com.Divar.DivarClient/documentation/Divar/RawPlugEventType/RPLocationChangeCity":{"role":"symbol","title":"RawPlugEventType.RPLocationChangeCity","fragments":[{"kind":"keyword","text":"case"},{"kind":"text","text":" "},{"kind":"identifier","text":"RPLocationChangeCity"}],"abstract":[],"identifier":"doc:\/\/com.Divar.DivarClient\/documentation\/Divar\/RawPlugEventType\/RPLocationChangeCity","kind":"symbol","type":"topic","url":"\/documentation\/divar\/rawplugeventtype\/rplocationchangecity"},"doc://com.Divar.DivarClient/documentation/Divar/RawPlugEventType/RPSearchDidDone":{"role":"symbol","title":"RawPlugEventType.RPSearchDidDone","fragments":[{"kind":"keyword","text":"case"},{"kind":"text","text":" "},{"kind":"identifier","text":"RPSearchDidDone"}],"abstract":[],"identifier":"doc:\/\/com.Divar.DivarClient\/documentation\/Divar\/RawPlugEventType\/RPSearchDidDone","kind":"symbol","type":"topic","url":"\/documentation\/divar\/rawplugeventtype\/rpsearchdiddone"},"doc://com.Divar.DivarClient/documentation/Divar/RawPlugEventType/RPNewPostListPageDidLoad":{"role":"symbol","title":"RawPlugEventType.RPNewPostListPageDidLoad","fragments":[{"kind":"keyword","text":"case"},{"kind":"text","text":" "},{"kind":"identifier","text":"RPNewPostListPageDidLoad"}],"abstract":[],"identifier":"doc:\/\/com.Divar.DivarClient\/documentation\/Divar\/RawPlugEventType\/RPNewPostListPageDidLoad","kind":"symbol","type":"topic","url":"\/documentation\/divar\/rawplugeventtype\/rpnewpostlistpagedidload"},"doc://com.Divar.DivarClient/documentation/Divar/RawPlugEventType/ShowCensoredLink":{"role":"symbol","title":"RawPlugEventType.ShowCensoredLink","fragments":[{"kind":"keyword","text":"case"},{"kind":"text","text":" "},{"kind":"identifier","text":"ShowCensoredLink"}],"abstract":[],"identifier":"doc:\/\/com.Divar.DivarClient\/documentation\/Divar\/RawPlugEventType\/ShowCensoredLink","kind":"symbol","type":"topic","url":"\/documentation\/divar\/rawplugeventtype\/showcensoredlink"},"doc://com.Divar.DivarClient/documentation/Divar/RawPlugEventType/RPListCategorySuggestion":{"role":"symbol","title":"RawPlugEventType.RPListCategorySuggestion","fragments":[{"kind":"keyword","text":"case"},{"kind":"text","text":" "},{"kind":"identifier","text":"RPListCategorySuggestion"}],"abstract":[],"identifier":"doc:\/\/com.Divar.DivarClient\/documentation\/Divar\/RawPlugEventType\/RPListCategorySuggestion","kind":"symbol","type":"topic","url":"\/documentation\/divar\/rawplugeventtype\/rplistcategorysuggestion"},"doc://com.Divar.DivarClient/documentation/Divar/RawPlugEventType/RPChatDidSendImage":{"role":"symbol","title":"RawPlugEventType.RPChatDidSendImage","fragments":[{"kind":"keyword","text":"case"},{"kind":"text","text":" "},{"kind":"identifier","text":"RPChatDidSendImage"}],"abstract":[],"identifier":"doc:\/\/com.Divar.DivarClient\/documentation\/Divar\/RawPlugEventType\/RPChatDidSendImage","kind":"symbol","type":"topic","url":"\/documentation\/divar\/rawplugeventtype\/rpchatdidsendimage"},"doc://com.Divar.DivarClient/documentation/Divar/RawPlugEventType/RPCHatAttachmentItemDidSelect":{"role":"symbol","title":"RawPlugEventType.RPCHatAttachmentItemDidSelect","fragments":[{"kind":"keyword","text":"case"},{"kind":"text","text":" "},{"kind":"identifier","text":"RPCHatAttachmentItemDidSelect"}],"abstract":[],"identifier":"doc:\/\/com.Divar.DivarClient\/documentation\/Divar\/RawPlugEventType\/RPCHatAttachmentItemDidSelect","kind":"symbol","type":"topic","url":"\/documentation\/divar\/rawplugeventtype\/rpchatattachmentitemdidselect"},"doc://com.Divar.DivarClient/documentation/Divar/RawPlugEventType/RPActionVoipAnswer":{"role":"symbol","title":"RawPlugEventType.RPActionVoipAnswer","fragments":[{"kind":"keyword","text":"case"},{"kind":"text","text":" "},{"kind":"identifier","text":"RPActionVoipAnswer"}],"abstract":[],"identifier":"doc:\/\/com.Divar.DivarClient\/documentation\/Divar\/RawPlugEventType\/RPActionVoipAnswer","kind":"symbol","type":"topic","url":"\/documentation\/divar\/rawplugeventtype\/rpactionvoipanswer"},"doc://com.Divar.DivarClient/documentation/Divar/RawPlugEventType/RPChatNotificationDidReceive":{"role":"symbol","title":"RawPlugEventType.RPChatNotificationDidReceive","fragments":[{"kind":"keyword","text":"case"},{"kind":"text","text":" "},{"kind":"identifier","text":"RPChatNotificationDidReceive"}],"abstract":[],"identifier":"doc:\/\/com.Divar.DivarClient\/documentation\/Divar\/RawPlugEventType\/RPChatNotificationDidReceive","kind":"symbol","type":"topic","url":"\/documentation\/divar\/rawplugeventtype\/rpchatnotificationdidreceive"},"doc://com.Divar.DivarClient/documentation/Divar/RawPlugEventType/RPSubmitVerificationCode":{"role":"symbol","title":"RawPlugEventType.RPSubmitVerificationCode","fragments":[{"kind":"keyword","text":"case"},{"kind":"text","text":" "},{"kind":"identifier","text":"RPSubmitVerificationCode"}],"abstract":[],"identifier":"doc:\/\/com.Divar.DivarClient\/documentation\/Divar\/RawPlugEventType\/RPSubmitVerificationCode","kind":"symbol","type":"topic","url":"\/documentation\/divar\/rawplugeventtype\/rpsubmitverificationcode"},"doc://com.Divar.DivarClient/documentation/Divar/RawPlugEventType/RPChatFormatNotSupported":{"role":"symbol","title":"RawPlugEventType.RPChatFormatNotSupported","fragments":[{"kind":"keyword","text":"case"},{"kind":"text","text":" "},{"kind":"identifier","text":"RPChatFormatNotSupported"}],"abstract":[],"identifier":"doc:\/\/com.Divar.DivarClient\/documentation\/Divar\/RawPlugEventType\/RPChatFormatNotSupported","kind":"symbol","type":"topic","url":"\/documentation\/divar\/rawplugeventtype\/rpchatformatnotsupported"},"doc://com.Divar.DivarClient/documentation/Divar/RawPlugEventType/RPOpenImagePreview":{"role":"symbol","title":"RawPlugEventType.RPOpenImagePreview","fragments":[{"kind":"keyword","text":"case"},{"kind":"text","text":" "},{"kind":"identifier","text":"RPOpenImagePreview"}],"abstract":[],"identifier":"doc:\/\/com.Divar.DivarClient\/documentation\/Divar\/RawPlugEventType\/RPOpenImagePreview","kind":"symbol","type":"topic","url":"\/documentation\/divar\/rawplugeventtype\/rpopenimagepreview"},"doc://com.Divar.DivarClient/documentation/Divar/RawPlugEventType/RPClickBlogPost":{"role":"symbol","title":"RawPlugEventType.RPClickBlogPost","fragments":[{"kind":"keyword","text":"case"},{"kind":"text","text":" "},{"kind":"identifier","text":"RPClickBlogPost"}],"abstract":[],"identifier":"doc:\/\/com.Divar.DivarClient\/documentation\/Divar\/RawPlugEventType\/RPClickBlogPost","kind":"symbol","type":"topic","url":"\/documentation\/divar\/rawplugeventtype\/rpclickblogpost"},"doc://com.Divar.DivarClient/documentation/Divar/RawPlugEventType/RPViewInspectionReport":{"role":"symbol","title":"RawPlugEventType.RPViewInspectionReport","fragments":[{"kind":"keyword","text":"case"},{"kind":"text","text":" "},{"kind":"identifier","text":"RPViewInspectionReport"}],"abstract":[],"identifier":"doc:\/\/com.Divar.DivarClient\/documentation\/Divar\/RawPlugEventType\/RPViewInspectionReport","kind":"symbol","type":"topic","url":"\/documentation\/divar\/rawplugeventtype\/rpviewinspectionreport"},"doc://com.Divar.DivarClient/documentation/Divar/RawPlugEventType/ChatSettingsItemClicked":{"role":"symbol","title":"RawPlugEventType.ChatSettingsItemClicked","fragments":[{"kind":"keyword","text":"case"},{"kind":"text","text":" "},{"kind":"identifier","text":"ChatSettingsItemClicked"}],"abstract":[],"identifier":"doc:\/\/com.Divar.DivarClient\/documentation\/Divar\/RawPlugEventType\/ChatSettingsItemClicked","kind":"symbol","type":"topic","url":"\/documentation\/divar\/rawplugeventtype\/chatsettingsitemclicked"},"doc://com.Divar.DivarClient/documentation/Divar/RawPlugEventType":{"role":"symbol","title":"RawPlugEventType","fragments":[{"kind":"keyword","text":"enum"},{"kind":"text","text":" "},{"kind":"identifier","text":"RawPlugEventType"}],"abstract":[],"identifier":"doc:\/\/com.Divar.DivarClient\/documentation\/Divar\/RawPlugEventType","kind":"symbol","type":"topic","navigatorTitle":[{"kind":"identifier","text":"RawPlugEventType"}],"url":"\/documentation\/divar\/rawplugeventtype"},"doc://com.Divar.DivarClient/documentation/Divar/RawPlugEventType/RPClickBulkLadder":{"role":"symbol","title":"RawPlugEventType.RPClickBulkLadder","fragments":[{"kind":"keyword","text":"case"},{"kind":"text","text":" "},{"kind":"identifier","text":"RPClickBulkLadder"}],"abstract":[],"identifier":"doc:\/\/com.Divar.DivarClient\/documentation\/Divar\/RawPlugEventType\/RPClickBulkLadder","kind":"symbol","type":"topic","url":"\/documentation\/divar\/rawplugeventtype\/rpclickbulkladder"},"doc://com.Divar.DivarClient/documentation/Divar/RawPlugEventType/RPLoadImage":{"role":"symbol","title":"RawPlugEventType.RPLoadImage","fragments":[{"kind":"keyword","text":"case"},{"kind":"text","text":" "},{"kind":"identifier","text":"RPLoadImage"}],"abstract":[],"identifier":"doc:\/\/com.Divar.DivarClient\/documentation\/Divar\/RawPlugEventType\/RPLoadImage","kind":"symbol","type":"topic","url":"\/documentation\/divar\/rawplugeventtype\/rploadimage"},"doc://com.Divar.DivarClient/documentation/Divar/RawPlugEventType/RPDivarDidOpen":{"role":"symbol","title":"RawPlugEventType.RPDivarDidOpen","fragments":[{"kind":"keyword","text":"case"},{"kind":"text","text":" "},{"kind":"identifier","text":"RPDivarDidOpen"}],"abstract":[],"identifier":"doc:\/\/com.Divar.DivarClient\/documentation\/Divar\/RawPlugEventType\/RPDivarDidOpen","kind":"symbol","type":"topic","url":"\/documentation\/divar\/rawplugeventtype\/rpdivardidopen"},"doc://com.Divar.DivarClient/documentation/Divar/RawPlugEventType/RPContactMethodDidSelect":{"role":"symbol","title":"RawPlugEventType.RPContactMethodDidSelect","fragments":[{"kind":"keyword","text":"case"},{"kind":"text","text":" "},{"kind":"identifier","text":"RPContactMethodDidSelect"}],"abstract":[],"identifier":"doc:\/\/com.Divar.DivarClient\/documentation\/Divar\/RawPlugEventType\/RPContactMethodDidSelect","kind":"symbol","type":"topic","url":"\/documentation\/divar\/rawplugeventtype\/rpcontactmethoddidselect"},"doc://com.Divar.DivarClient/documentation/Divar/RawPlugEventType/RPSuggestionDidSelect":{"role":"symbol","title":"RawPlugEventType.RPSuggestionDidSelect","fragments":[{"kind":"keyword","text":"case"},{"kind":"text","text":" "},{"kind":"identifier","text":"RPSuggestionDidSelect"}],"abstract":[],"identifier":"doc:\/\/com.Divar.DivarClient\/documentation\/Divar\/RawPlugEventType\/RPSuggestionDidSelect","kind":"symbol","type":"topic","url":"\/documentation\/divar\/rawplugeventtype\/rpsuggestiondidselect"},"doc://com.Divar.DivarClient/documentation/Divar/RawPlugEventType/DivarForBusinesses":{"role":"symbol","title":"RawPlugEventType.DivarForBusinesses","fragments":[{"kind":"keyword","text":"case"},{"kind":"text","text":" "},{"kind":"identifier","text":"DivarForBusinesses"}],"abstract":[],"identifier":"doc:\/\/com.Divar.DivarClient\/documentation\/Divar\/RawPlugEventType\/DivarForBusinesses","kind":"symbol","type":"topic","url":"\/documentation\/divar\/rawplugeventtype\/divarforbusinesses"},"doc://com.Divar.DivarClient/documentation/Divar/RawPlugEventType/RPHistoryDidSelect":{"role":"symbol","title":"RawPlugEventType.RPHistoryDidSelect","fragments":[{"kind":"keyword","text":"case"},{"kind":"text","text":" "},{"kind":"identifier","text":"RPHistoryDidSelect"}],"abstract":[],"identifier":"doc:\/\/com.Divar.DivarClient\/documentation\/Divar\/RawPlugEventType\/RPHistoryDidSelect","kind":"symbol","type":"topic","url":"\/documentation\/divar\/rawplugeventtype\/rphistorydidselect"},"doc://com.Divar.DivarClient/documentation/Divar/RawPlugEventType/RPActionVoipIncoming":{"role":"symbol","title":"RawPlugEventType.RPActionVoipIncoming","fragments":[{"kind":"keyword","text":"case"},{"kind":"text","text":" "},{"kind":"identifier","text":"RPActionVoipIncoming"}],"abstract":[],"identifier":"doc:\/\/com.Divar.DivarClient\/documentation\/Divar\/RawPlugEventType\/RPActionVoipIncoming","kind":"symbol","type":"topic","url":"\/documentation\/divar\/rawplugeventtype\/rpactionvoipincoming"},"doc://com.Divar.DivarClient/documentation/Divar/RawPlugEventType/RPPostDidBookmarked":{"role":"symbol","title":"RawPlugEventType.RPPostDidBookmarked","fragments":[{"kind":"keyword","text":"case"},{"kind":"text","text":" "},{"kind":"identifier","text":"RPPostDidBookmarked"}],"abstract":[],"identifier":"doc:\/\/com.Divar.DivarClient\/documentation\/Divar\/RawPlugEventType\/RPPostDidBookmarked","kind":"symbol","type":"topic","url":"\/documentation\/divar\/rawplugeventtype\/rppostdidbookmarked"},"doc://com.Divar.DivarClient/documentation/Divar/RawPlugEventType/Equatable-Implementations":{"role":"collectionGroup","title":"Equatable Implementations","abstract":[],"identifier":"doc:\/\/com.Divar.DivarClient\/documentation\/Divar\/RawPlugEventType\/Equatable-Implementations","kind":"article","type":"topic","url":"\/documentation\/divar\/rawplugeventtype\/equatable-implementations"},"doc://com.Divar.DivarClient/documentation/Divar/RawPlugEventType/RPChatCallCheckDidSelect":{"role":"symbol","title":"RawPlugEventType.RPChatCallCheckDidSelect","fragments":[{"kind":"keyword","text":"case"},{"kind":"text","text":" "},{"kind":"identifier","text":"RPChatCallCheckDidSelect"}],"abstract":[],"identifier":"doc:\/\/com.Divar.DivarClient\/documentation\/Divar\/RawPlugEventType\/RPChatCallCheckDidSelect","kind":"symbol","type":"topic","url":"\/documentation\/divar\/rawplugeventtype\/rpchatcallcheckdidselect"},"doc://com.Divar.DivarClient/documentation/Divar/RawPlugEventType/RPSubmitPostSaveLocation":{"role":"symbol","title":"RawPlugEventType.RPSubmitPostSaveLocation","fragments":[{"kind":"keyword","text":"case"},{"kind":"text","text":" "},{"kind":"identifier","text":"RPSubmitPostSaveLocation"}],"abstract":[],"identifier":"doc:\/\/com.Divar.DivarClient\/documentation\/Divar\/RawPlugEventType\/RPSubmitPostSaveLocation","kind":"symbol","type":"topic","url":"\/documentation\/divar\/rawplugeventtype\/rpsubmitpostsavelocation"},"doc://com.Divar.DivarClient/documentation/Divar/RawPlugEventType/RPCityDidChange":{"role":"symbol","title":"RawPlugEventType.RPCityDidChange","fragments":[{"kind":"keyword","text":"case"},{"kind":"text","text":" "},{"kind":"identifier","text":"RPCityDidChange"}],"abstract":[],"identifier":"doc:\/\/com.Divar.DivarClient\/documentation\/Divar\/RawPlugEventType\/RPCityDidChange","kind":"symbol","type":"topic","url":"\/documentation\/divar\/rawplugeventtype\/rpcitydidchange"},"doc://com.Divar.DivarClient/documentation/Divar/RawPlugEventType/RPFilterDialogDidClose":{"role":"symbol","title":"RawPlugEventType.RPFilterDialogDidClose","fragments":[{"kind":"keyword","text":"case"},{"kind":"text","text":" "},{"kind":"identifier","text":"RPFilterDialogDidClose"}],"abstract":[],"identifier":"doc:\/\/com.Divar.DivarClient\/documentation\/Divar\/RawPlugEventType\/RPFilterDialogDidClose","kind":"symbol","type":"topic","url":"\/documentation\/divar\/rawplugeventtype\/rpfilterdialogdidclose"},"doc://com.Divar.DivarClient/documentation/Divar/RawPlugEventType/ChatSelectConversation":{"role":"symbol","title":"RawPlugEventType.ChatSelectConversation","fragments":[{"kind":"keyword","text":"case"},{"kind":"text","text":" "},{"kind":"identifier","text":"ChatSelectConversation"}],"abstract":[],"identifier":"doc:\/\/com.Divar.DivarClient\/documentation\/Divar\/RawPlugEventType\/ChatSelectConversation","kind":"symbol","type":"topic","url":"\/documentation\/divar\/rawplugeventtype\/chatselectconversation"},"doc://com.Divar.DivarClient/documentation/Divar/RawPlugEventType/RPClickSimilarPost":{"role":"symbol","title":"RawPlugEventType.RPClickSimilarPost","fragments":[{"kind":"keyword","text":"case"},{"kind":"text","text":" "},{"kind":"identifier","text":"RPClickSimilarPost"}],"abstract":[],"identifier":"doc:\/\/com.Divar.DivarClient\/documentation\/Divar\/RawPlugEventType\/RPClickSimilarPost","kind":"symbol","type":"topic","url":"\/documentation\/divar\/rawplugeventtype\/rpclicksimilarpost"},"doc://com.Divar.DivarClient/documentation/Divar/RawPlugEventType/RPSubmitRemovePhoto":{"role":"symbol","title":"RawPlugEventType.RPSubmitRemovePhoto","fragments":[{"kind":"keyword","text":"case"},{"kind":"text","text":" "},{"kind":"identifier","text":"RPSubmitRemovePhoto"}],"abstract":[],"identifier":"doc:\/\/com.Divar.DivarClient\/documentation\/Divar\/RawPlugEventType\/RPSubmitRemovePhoto","kind":"symbol","type":"topic","url":"\/documentation\/divar\/rawplugeventtype\/rpsubmitremovephoto"},"doc://com.Divar.DivarClient/documentation/Divar/RawPlugEventType/RPViewDealershipManagmentPage":{"role":"symbol","title":"RawPlugEventType.RPViewDealershipManagmentPage","fragments":[{"kind":"keyword","text":"case"},{"kind":"text","text":" "},{"kind":"identifier","text":"RPViewDealershipManagmentPage"}],"abstract":[],"identifier":"doc:\/\/com.Divar.DivarClient\/documentation\/Divar\/RawPlugEventType\/RPViewDealershipManagmentPage","kind":"symbol","type":"topic","url":"\/documentation\/divar\/rawplugeventtype\/rpviewdealershipmanagmentpage"},"doc://com.Divar.DivarClient/documentation/Divar/RawPlugEventType/RPActionVoipTerminate":{"role":"symbol","title":"RawPlugEventType.RPActionVoipTerminate","fragments":[{"kind":"keyword","text":"case"},{"kind":"text","text":" "},{"kind":"identifier","text":"RPActionVoipTerminate"}],"abstract":[],"identifier":"doc:\/\/com.Divar.DivarClient\/documentation\/Divar\/RawPlugEventType\/RPActionVoipTerminate","kind":"symbol","type":"topic","url":"\/documentation\/divar\/rawplugeventtype\/rpactionvoipterminate"},"doc://com.Divar.DivarClient/documentation/Divar/RawPlugEventType/RPRegisterDealership":{"role":"symbol","title":"RawPlugEventType.RPRegisterDealership","fragments":[{"kind":"keyword","text":"case"},{"kind":"text","text":" "},{"kind":"identifier","text":"RPRegisterDealership"}],"abstract":[],"identifier":"doc:\/\/com.Divar.DivarClient\/documentation\/Divar\/RawPlugEventType\/RPRegisterDealership","kind":"symbol","type":"topic","url":"\/documentation\/divar\/rawplugeventtype\/rpregisterdealership"},"doc://com.Divar.DivarClient/SQ":{"type":"unresolvable","title":"Swift.Equatable","identifier":"doc:\/\/com.Divar.DivarClient\/SQ"},"doc://com.Divar.DivarClient/documentation/Divar/RawPlugEventType/RPBuyerInspectionRequest":{"role":"symbol","title":"RawPlugEventType.RPBuyerInspectionRequest","fragments":[{"kind":"keyword","text":"case"},{"kind":"text","text":" "},{"kind":"identifier","text":"RPBuyerInspectionRequest"}],"abstract":[],"identifier":"doc:\/\/com.Divar.DivarClient\/documentation\/Divar\/RawPlugEventType\/RPBuyerInspectionRequest","kind":"symbol","type":"topic","url":"\/documentation\/divar\/rawplugeventtype\/rpbuyerinspectionrequest"},"doc://com.Divar.DivarClient/documentation/Divar/RawPlugEventType/Approved":{"role":"symbol","title":"RawPlugEventType.Approved","fragments":[{"kind":"keyword","text":"case"},{"kind":"text","text":" "},{"kind":"identifier","text":"Approved"}],"abstract":[],"identifier":"doc:\/\/com.Divar.DivarClient\/documentation\/Divar\/RawPlugEventType\/Approved","kind":"symbol","type":"topic","url":"\/documentation\/divar\/rawplugeventtype\/approved"},"doc://com.Divar.DivarClient/documentation/Divar/RawPlugEventType/RPActionVoipClick":{"role":"symbol","title":"RawPlugEventType.RPActionVoipClick","fragments":[{"kind":"keyword","text":"case"},{"kind":"text","text":" "},{"kind":"identifier","text":"RPActionVoipClick"}],"abstract":[],"identifier":"doc:\/\/com.Divar.DivarClient\/documentation\/Divar\/RawPlugEventType\/RPActionVoipClick","kind":"symbol","type":"topic","url":"\/documentation\/divar\/rawplugeventtype\/rpactionvoipclick"},"doc://com.Divar.DivarClient/documentation/Divar/RawPlugEventType/RPClickBrandType":{"role":"symbol","title":"RawPlugEventType.RPClickBrandType","fragments":[{"kind":"keyword","text":"case"},{"kind":"text","text":" "},{"kind":"identifier","text":"RPClickBrandType"}],"abstract":[],"identifier":"doc:\/\/com.Divar.DivarClient\/documentation\/Divar\/RawPlugEventType\/RPClickBrandType","kind":"symbol","type":"topic","url":"\/documentation\/divar\/rawplugeventtype\/rpclickbrandtype"},"doc://com.Divar.DivarClient/documentation/Divar/RawPlugEventType/RPOtherValuesDidSelect":{"role":"symbol","title":"RawPlugEventType.RPOtherValuesDidSelect","fragments":[{"kind":"keyword","text":"case"},{"kind":"text","text":" "},{"kind":"identifier","text":"RPOtherValuesDidSelect"}],"abstract":[],"identifier":"doc:\/\/com.Divar.DivarClient\/documentation\/Divar\/RawPlugEventType\/RPOtherValuesDidSelect","kind":"symbol","type":"topic","url":"\/documentation\/divar\/rawplugeventtype\/rpothervaluesdidselect"},"doc://com.Divar.DivarClient/documentation/Divar/RawPlugEventType/RPLocationChangeNeighbor":{"role":"symbol","title":"RawPlugEventType.RPLocationChangeNeighbor","fragments":[{"kind":"keyword","text":"case"},{"kind":"text","text":" "},{"kind":"identifier","text":"RPLocationChangeNeighbor"}],"abstract":[],"identifier":"doc:\/\/com.Divar.DivarClient\/documentation\/Divar\/RawPlugEventType\/RPLocationChangeNeighbor","kind":"symbol","type":"topic","url":"\/documentation\/divar\/rawplugeventtype\/rplocationchangeneighbor"},"doc://com.Divar.DivarClient/documentation/Divar/RawPlugEventType/RPClickAgencyInPost":{"role":"symbol","title":"RawPlugEventType.RPClickAgencyInPost","fragments":[{"kind":"keyword","text":"case"},{"kind":"text","text":" "},{"kind":"identifier","text":"RPClickAgencyInPost"}],"abstract":[],"identifier":"doc:\/\/com.Divar.DivarClient\/documentation\/Divar\/RawPlugEventType\/RPClickAgencyInPost","kind":"symbol","type":"topic","url":"\/documentation\/divar\/rawplugeventtype\/rpclickagencyinpost"},"doc://com.Divar.DivarClient/documentation/Divar/RawPlugEventType/RPSubmitNextPage":{"role":"symbol","title":"RawPlugEventType.RPSubmitNextPage","fragments":[{"kind":"keyword","text":"case"},{"kind":"text","text":" "},{"kind":"identifier","text":"RPSubmitNextPage"}],"abstract":[],"identifier":"doc:\/\/com.Divar.DivarClient\/documentation\/Divar\/RawPlugEventType\/RPSubmitNextPage","kind":"symbol","type":"topic","url":"\/documentation\/divar\/rawplugeventtype\/rpsubmitnextpage"},"doc://com.Divar.DivarClient/documentation/Divar/RawPlugEventType/RPOtherFiltersDidSelect":{"role":"symbol","title":"RawPlugEventType.RPOtherFiltersDidSelect","fragments":[{"kind":"keyword","text":"case"},{"kind":"text","text":" "},{"kind":"identifier","text":"RPOtherFiltersDidSelect"}],"abstract":[],"identifier":"doc:\/\/com.Divar.DivarClient\/documentation\/Divar\/RawPlugEventType\/RPOtherFiltersDidSelect","kind":"symbol","type":"topic","url":"\/documentation\/divar\/rawplugeventtype\/rpotherfiltersdidselect"},"doc://com.Divar.DivarClient/documentation/Divar/RawPlugEventType/ChatSettingClicked":{"role":"symbol","title":"RawPlugEventType.ChatSettingClicked","fragments":[{"kind":"keyword","text":"case"},{"kind":"text","text":" "},{"kind":"identifier","text":"ChatSettingClicked"}],"abstract":[],"identifier":"doc:\/\/com.Divar.DivarClient\/documentation\/Divar\/RawPlugEventType\/ChatSettingClicked","kind":"symbol","type":"topic","url":"\/documentation\/divar\/rawplugeventtype\/chatsettingclicked"},"doc://com.Divar.DivarClient/documentation/Divar/RawPlugEventType/RPPreviewSimilarPosts":{"role":"symbol","title":"RawPlugEventType.RPPreviewSimilarPosts","fragments":[{"kind":"keyword","text":"case"},{"kind":"text","text":" "},{"kind":"identifier","text":"RPPreviewSimilarPosts"}],"abstract":[],"identifier":"doc:\/\/com.Divar.DivarClient\/documentation\/Divar\/RawPlugEventType\/RPPreviewSimilarPosts","kind":"symbol","type":"topic","url":"\/documentation\/divar\/rawplugeventtype\/rppreviewsimilarposts"},"doc://com.Divar.DivarClient/SH":{"type":"unresolvable","title":"Swift.Hashable","identifier":"doc:\/\/com.Divar.DivarClient\/SH"},"doc://com.Divar.DivarClient/documentation/Divar/RawPlugEventType/PostchiNotification":{"role":"symbol","title":"RawPlugEventType.PostchiNotification","fragments":[{"kind":"keyword","text":"case"},{"kind":"text","text":" "},{"kind":"identifier","text":"PostchiNotification"}],"abstract":[],"identifier":"doc:\/\/com.Divar.DivarClient\/documentation\/Divar\/RawPlugEventType\/PostchiNotification","kind":"symbol","type":"topic","url":"\/documentation\/divar\/rawplugeventtype\/postchinotification"},"doc://com.Divar.DivarClient/documentation/Divar/RawPlugEventType/RPFilterItemDidClear":{"role":"symbol","title":"RawPlugEventType.RPFilterItemDidClear","fragments":[{"kind":"keyword","text":"case"},{"kind":"text","text":" "},{"kind":"identifier","text":"RPFilterItemDidClear"}],"abstract":[],"identifier":"doc:\/\/com.Divar.DivarClient\/documentation\/Divar\/RawPlugEventType\/RPFilterItemDidClear","kind":"symbol","type":"topic","url":"\/documentation\/divar\/rawplugeventtype\/rpfilteritemdidclear"}}}